arnelify-ffi.cpython-311-x86_64-linux-gnu.so
arnelify/__init__.py
arnelify/index.py
arnelify/contracts/__init__.py
arnelify/contracts/res.py
arnelify-0.5.0.dist-info/LICENSE
arnelify-0.5.0.dist-info/METADATA
arnelify-0.5.0.dist-info/WHEEL
arnelify-0.5.0.dist-info/top_level.txt
arnelify-0.5.0.dist-info/RECORD
