Metadata-Version: 2.1
Name: arnelify
Version: 0.5.0
Summary: Minimalistic dynamic library which is an SDK written in C and C++.
Home-page: https://github.com/arnelify/arnelify-python
Author: Arnelify
License: MIT
Keywords: arnelify arnelify-python arnelify-sdk arnelify-sdk-python
Classifier: Programming Language :: Python :: 3
License-File: LICENSE
Requires-Dist: cffi
Requires-Dist: setuptools
Requires-Dist: wheel
